{
  "document_id": "00324fabf598c68fe0e88707b3929d212d22a65a526b923496b49a2e71a46fdd",
  "document_metadata": {
    "id": "00324fabf598c68fe0e88707b3929d212d22a65a526b923496b49a2e71a46fdd",
    "date": 20251023,
    "publisher_id": "242e6934-d98d-4b91-a9a9-f6a425f85938",
    "image": "https://bloximages.newyork1.vip.townnews.com/richmond.com/content/tncms/assets/v3/editorial/8/b8/8b8c8cff-5777-4e29-93ea-184e6cba8673/68f8f2417e7c9.preview.jpg?resize=640%2C427",
    "date_year": 2025,
    "date_month": 10,
    "crawl_date": "2025-10-23T21:32:42.521291032Z",
    "date_day": 23,
    "title": "Where to find the best Halloween decorations around Richmond",
    "url": "https://richmond.com/life-entertainment/local/article_8b8c8cff-5777-4e29-93ea-184e6cba8673.html",
    "url2": "https://richmond.com/life-entertainment/local/article_8b8c8cff-5777-4e29-93ea-184e6cba8673.html",
    "domain": "richmond.com",
    "lang": "unknown",
    "published_date": "2025-10-23T06:30:00-04:00",
    "has_markdown": true,
    "markdown_input_text_type": "Unknown",
    "markdown_converter_type": "markdownify-with-preprocessing",
    "has_processed_text": true,
    "contentType": "web",
    "metadataVersion": 1,
    "dir": "242e6934-d98d-4b91-a9a9-f6a425f85938",
    "skip_servicebusmessage_for_ingestion": false,
    "rawType": "json",
    "publisherId": "242e6934-d98d-4b91-a9a9-f6a425f85938",
    "documentId": "00324fabf598c68fe0e88707b3929d212d22a65a526b923496b49a2e71a46fdd",
    "rawcontent_created": "2025-10-23T21:32:43.571000",
    "source": "Richmond Times-Dispatch",
    "favicon": "https://www.google.com/s2/favicons?sz=128&domain=richmond.com",
    "favicon40": "https://www.google.com/s2/favicons?sz=40&domain=richmond.com",
    "favicon24": "https://www.google.com/s2/favicons?sz=24&domain=richmond.com",
    "first_words": "Richmond’s neighborhoods come alive each October with the Halloween spirit, ranging from downright frightening to kid-friendly whimsy. ,There are animatronics, zombie takeovers, parades and plenty of 12-foot skeletons standing guard. ,Halloween is near, so let the boos begin. , ,In North Chesterfield at 10533 Ashburn Road, Julie Watson and Bill McNeill, both 58, are ready to collect some screams. Every inch of the yard is part of the performance. There’s fog, homemade tombstones, Annabelle hanging in the trees, and scare actors hiding in plain sight. What started as small yard decorations has turned into a full-scale production."
  },
  "publisher_metadata": {
    "id": "242e6934-d98d-4b91-a9a9-f6a425f85938",
    "group_id": "d9d5151e-0891-4887-836c-050cdf8f19c3",
    "name": "Richmond Times-Dispatch",
    "domain": "richmond.com",
    "location": "United States",
    "country": "United States",
    "location1": null,
    "location2": null,
    "category": null,
    "index_name": "lee_enterprises_index_v2",
    "network_ids": []
  },
  "content_metadata": {
    "document_title_txt": "Where to find the best Halloween decorations around Richmond",
    "document_authors_txt": [],
    "hash": "111e5ac8d92339d2d895f1cd38769f0680f8f27f635c773efa962128e4dc053a"
  },
  "ingest_metadata_from_chunks": {
    "version": "2.3",
    "date": "2025-10-23",
    "chunking": {
      "chunks_count": 9
    },
    "context_generating": {
      "strategy": "none"
    },
    "embedding": {
      "provider": "voyage",
      "model": "voyage-3-large",
      "dimension": 2048,
      "data_type": "binary"
    }
  },
  "chunks": [
    {
      "include": true,
      "schema_version": "2.0",
      "chunk_metadata": {
        "id": "00324fabf598c68fe0e88707b3929d212d22a65a526b923496b49a2e71a46fdd-4",
        "idx": 4,
        "hash": "37ea2bed0264d9ebe2ea56bc47eb78c73d29f21c0efbe4361cd9a1759dfafb78"
      },
      "content_original": ",\n\nThis year, they’re extending their display to include a Halloween tunnel in the driveway and another in the backyard.\n\n,\n\n“That one’s going to be a little bit scarier,” she said. “We’re going to hire some actors, volunteer actors, to do some little jump scares. We have all these ambitious ideas, and trying to make them come to real life is a challenge but we enjoy it, myself and my husband. As long as we’ve got good knees and a good back.”\n\n,\n\nThe couple starts prepping early.\n\n,\n\n“We start staging in the backyard in June to make sure they’re working, if they need any touch-ups or repairs,” she said. “We had one of the 12-foot skeletons fall over last year, so his ribs were broken. So right now, we’re doing some plastic surgery on him.”\n\n,\n\nHer two youngest children still help out, offering ideas and dressing up every year. “Because you live in my house, you got to dress up,” she said.",
      "content": ",\n\nThis year, they’re extending their display to include a Halloween tunnel in the driveway and another in the backyard.\n\n,\n\n“That one’s going to be a little bit scarier,” she said. “We’re going to hire some actors, volunteer actors, to do some little jump scares. We have all these ambitious ideas, and trying to make them come to real life is a challenge but we enjoy it, myself and my husband. As long as we’ve got good knees and a good back.”\n\n,\n\nThe couple starts prepping early.\n\n,\n\n“We start staging in the backyard in June to make sure they’re working, if they need any touch-ups or repairs,” she said. “We had one of the 12-foot skeletons fall over last year, so his ribs were broken. So right now, we’re doing some plastic surgery on him.”\n\n,\n\nHer two youngest children still help out, offering ideas and dressing up every year. “Because you live in my house, you got to dress up,” she said."
    },
    {
      "include": true,
      "schema_version": "2.0",
      "chunk_metadata": {
        "id": "00324fabf598c68fe0e88707b3929d212d22a65a526b923496b49a2e71a46fdd-6",
        "idx": 6,
        "hash": "af5be7ada43934ad79c7f98c3fa981028ba76dd35f8f6d26e09b235efcf31ffa"
      },
      "content_original": ",\n\nHead to **2105 Maplewood Road** for the Dark Woods of Lakeside or 9420 Gayton Road for skeletons, lights, witches, cauldrons and giant spiders.\n\n,\n\nIf you’re looking for something more fanciful, head to **3433 Floyd Ave.** in the Museum District for the Harry Potter House where Kyle and Sarah Rasmussen have turned their house into a page from a book.\n\n,\n\n“Halloween has always been a big thing in my family. My parents both enjoyed Halloween and decorated a lot when I was a kid,” Kyle said. “I’ve done Harry Potter the last six years that we’ve lived in Richmond. Each year, we do the next book.”\n\n,\n\nThis year is “Harry Potter and the Half-Blood Prince.”\n\n,\n\n“Every year there’s some old favorites, like the werewolves and the spiders and the dragon on top of the carport,” she said. “But the whole front of the house is completely different.”\n\n,\n\nThe house has become a local favorite and a social media hit.\n\n,",
      "content": ",\n\nHead to **2105 Maplewood Road** for the Dark Woods of Lakeside or 9420 Gayton Road for skeletons, lights, witches, cauldrons and giant spiders.\n\n,\n\nIf you’re looking for something more fanciful, head to **3433 Floyd Ave.** in the Museum District for the Harry Potter House where Kyle and Sarah Rasmussen have turned their house into a page from a book.\n\n,\n\n“Halloween has always been a big thing in my family. My parents both enjoyed Halloween and decorated a lot when I was a kid,” Kyle said. “I’ve done Harry Potter the last six years that we’ve lived in Richmond. Each year, we do the next book.”\n\n,\n\nThis year is “Harry Potter and the Half-Blood Prince.”\n\n,\n\n“Every year there’s some old favorites, like the werewolves and the spiders and the dragon on top of the carport,” she said. “But the whole front of the house is completely different.”\n\n,\n\nThe house has become a local favorite and a social media hit.\n\n,"
    },
    {
      "include": true,
      "schema_version": "2.0",
      "chunk_metadata": {
        "id": "00324fabf598c68fe0e88707b3929d212d22a65a526b923496b49a2e71a46fdd-7",
        "idx": 7,
        "hash": "da3f24fe005e8d5ca1aadbef43b15c7e2c3e4bad8bff96992bac211cd177ba69"
      },
      "content_original": ",\n\nThe house has become a local favorite and a social media hit.\n\n,\n\n“We usually have a lot of people stopping by,” he said. “Towards Halloween, we’ll probably get like 50 to 100 people during the day that will walk by it.”\n\n,\n\nAt night, Kyle says it’s too many to count.\n\n,\n\nPreparation starts early. “I used to wait till the first week of October, but since we have two small kids now, I start the second week of September just because it takes a little bit longer. And that time only gives me so much time to put stuff up.”\n\n,\n\nIn Henrico, **[The Haunt in Chamberlayne Farms](https://www.facebook.com/profile.php?id=61558301124456)** is back with a haunted walk-through experience at 5914 Chamberlayne Road.\n\n,\n\nOregon Hill has many Halloween decorated houses in preparation for the **[All the Saints Theater Company’s 20th annual Halloween Parade](https://www.facebook.com/allthesaintstheatercompany)** on Oct. 31.\n\n,",
      "content": ",\n\nThe house has become a local favorite and a social media hit.\n\n,\n\n“We usually have a lot of people stopping by,” he said. “Towards Halloween, we’ll probably get like 50 to 100 people during the day that will walk by it.”\n\n,\n\nAt night, Kyle says it’s too many to count.\n\n,\n\nPreparation starts early. “I used to wait till the first week of October, but since we have two small kids now, I start the second week of September just because it takes a little bit longer. And that time only gives me so much time to put stuff up.”\n\n,\n\nIn Henrico, **[The Haunt in Chamberlayne Farms](https://www.facebook.com/profile.php?id=61558301124456)** is back with a haunted walk-through experience at 5914 Chamberlayne Road.\n\n,\n\nOregon Hill has many Halloween decorated houses in preparation for the **[All the Saints Theater Company’s 20th annual Halloween Parade](https://www.facebook.com/allthesaintstheatercompany)** on Oct. 31.\n\n,"
    },
    {
      "include": true,
      "schema_version": "2.0",
      "chunk_metadata": {
        "id": "00324fabf598c68fe0e88707b3929d212d22a65a526b923496b49a2e71a46fdd-1",
        "idx": 1,
        "hash": "71707567b3433ad41e2ca1edd4b02c28bfec07e75bddc5b04f92346031fe7add"
      },
      "content_original": ",\n\nIn North Chesterfield at **10533 Ashburn Road,** Julie Watson and Bill McNeill, both 58, are ready to collect some screams. Every inch of the yard is part of the performance. There’s fog, homemade tombstones, Annabelle hanging in the trees, and scare actors hiding in plain sight. What started as small yard decorations has turned into a full-scale production.\n\n,\n\nWatson says Halloween has always been a favorite holiday. “It comes from a very young age. I love dressing up,” she said. “You get dressed up and you get candy. What kid does not want to do that?”\n\n,\n\nThat love of Halloween rolled over into making costumes for her children, doing hands-on DIY projects, and entering contests.\n\n,\n\nHer top costumes include a Rubik’s cube and a Chinese food to-go box for her son. One year, he won three costume contests helping Julie secure $3,000 off of his braces.",
      "content": ",\n\nIn North Chesterfield at **10533 Ashburn Road,** Julie Watson and Bill McNeill, both 58, are ready to collect some screams. Every inch of the yard is part of the performance. There’s fog, homemade tombstones, Annabelle hanging in the trees, and scare actors hiding in plain sight. What started as small yard decorations has turned into a full-scale production.\n\n,\n\nWatson says Halloween has always been a favorite holiday. “It comes from a very young age. I love dressing up,” she said. “You get dressed up and you get candy. What kid does not want to do that?”\n\n,\n\nThat love of Halloween rolled over into making costumes for her children, doing hands-on DIY projects, and entering contests.\n\n,\n\nHer top costumes include a Rubik’s cube and a Chinese food to-go box for her son. One year, he won three costume contests helping Julie secure $3,000 off of his braces."
    },
    {
      "include": true,
      "schema_version": "2.0",
      "chunk_metadata": {
        "id": "00324fabf598c68fe0e88707b3929d212d22a65a526b923496b49a2e71a46fdd-5",
        "idx": 5,
        "hash": "c06401174cd96ecbe269759f28405922c329fc9df8197f43f21a84ff4063d8d3"
      },
      "content_original": ", [![](https://bloximages.newyork1.vip.townnews.com/richmond.com/content/tncms/assets/v3/editorial/1/30/130bc762-ea2c-4d10-82dd-f4f3d9f0f935/68f7036113997.image.jpg?resize=100%2C75)](https://richmond.com/image_130bc762-ea2c-4d10-82dd-f4f3d9f0f935.html)\n\n## [Harry Potter house on Floyd Ave.](https://richmond.com/image_130bc762-ea2c-4d10-82dd-f4f3d9f0f935.html)\n\nEvery year, the Harry Potter house at 3433 Floyd Ave. gets decorated to the theme of a different Harry Potter book.\n\n,\n\n**More must-see Halloween houses around Richmond**The app Fright maps has an up-to-date list of decorated Halloween houses in the area like the haunted house at **4913 Sadler Glen Place in Glen Allen** with plenty of pumpkins, tombstones and even Jack Skellington.\n\n,",
      "content": ", [![](https://bloximages.newyork1.vip.townnews.com/richmond.com/content/tncms/assets/v3/editorial/1/30/130bc762-ea2c-4d10-82dd-f4f3d9f0f935/68f7036113997.image.jpg?resize=100%2C75)](https://richmond.com/image_130bc762-ea2c-4d10-82dd-f4f3d9f0f935.html)\n\n## [Harry Potter house on Floyd Ave.](https://richmond.com/image_130bc762-ea2c-4d10-82dd-f4f3d9f0f935.html)\n\nEvery year, the Harry Potter house at 3433 Floyd Ave. gets decorated to the theme of a different Harry Potter book.\n\n,\n\n**More must-see Halloween houses around Richmond**The app Fright maps has an up-to-date list of decorated Halloween houses in the area like the haunted house at **4913 Sadler Glen Place in Glen Allen** with plenty of pumpkins, tombstones and even Jack Skellington.\n\n,"
    },
    {
      "include": true,
      "schema_version": "2.0",
      "chunk_metadata": {
        "id": "00324fabf598c68fe0e88707b3929d212d22a65a526b923496b49a2e71a46fdd-3",
        "idx": 3,
        "hash": "87b721072ec0ae02ce52ad9e0981e0d326ccd7225575c639c3673a13bf7f87bc"
      },
      "content_original": ",\n\n“We like putting a smile on the kids’ faces,” she added. “Our house is off Huguenot Road between St. Edward’s Church and Huguenot Church, so we get a lot of traffic. When schools let out, there’s a line of cars just rolling slowly, looking at our display.”\n\n, [![](https://bloximages.newyork1.vip.townnews.com/richmond.com/content/tncms/assets/v3/editorial/e/e9/ee9f5caa-989a-476e-b125-d0750cf9bfff/68f8ed7e638c4.image.jpg?resize=100%2C67)](https://richmond.com/image_ee9f5caa-989a-476e-b125-d0750cf9bfff.html)\n\n## [10xx25-rtd-met-halloween](https://richmond.com/image_ee9f5caa-989a-476e-b125-d0750cf9bfff.html)\n\nA giant animatronic werewolf is part of the halloween decorations at 10533 Ashburn Road in North Chesterfield.\n\n,",
      "content": ",\n\n“We like putting a smile on the kids’ faces,” she added. “Our house is off Huguenot Road between St. Edward’s Church and Huguenot Church, so we get a lot of traffic. When schools let out, there’s a line of cars just rolling slowly, looking at our display.”\n\n, [![](https://bloximages.newyork1.vip.townnews.com/richmond.com/content/tncms/assets/v3/editorial/e/e9/ee9f5caa-989a-476e-b125-d0750cf9bfff/68f8ed7e638c4.image.jpg?resize=100%2C67)](https://richmond.com/image_ee9f5caa-989a-476e-b125-d0750cf9bfff.html)\n\n## [10xx25-rtd-met-halloween](https://richmond.com/image_ee9f5caa-989a-476e-b125-d0750cf9bfff.html)\n\nA giant animatronic werewolf is part of the halloween decorations at 10533 Ashburn Road in North Chesterfield.\n\n,"
    },
    {
      "include": true,
      "schema_version": "2.0",
      "chunk_metadata": {
        "id": "00324fabf598c68fe0e88707b3929d212d22a65a526b923496b49a2e71a46fdd-2",
        "idx": 2,
        "hash": "8ff6a2f49b18c53bcf63e66f47de144050d20657cca7e60c7bcfe9953b8dcefd"
      },
      "content_original": ", [![](https://bloximages.newyork1.vip.townnews.com/richmond.com/content/tncms/assets/v3/editorial/a/f2/af22ec18-2ba4-4fb2-b6da-3375e85df917/68f8edb2b810b.image.jpg?resize=100%2C67)](https://richmond.com/image_af22ec18-2ba4-4fb2-b6da-3375e85df917.html)\n\n## [10xx25-rtd-met-halloween](https://richmond.com/image_af22ec18-2ba4-4fb2-b6da-3375e85df917.html)\n\n“We like putting a smile on the kids’ faces,” Julie Watson said. “When schools let out, there’s a line of cars just rolling slowly, looking at our display.”\n\n,\n,\n\n“For myself, it was the pumpkin scarecrow. I sat in front of the casket, slumped over in a chair, and then I would tap on the casket, and I’d say, ‘Boo.’ They thought I was a prop,” she said. “We started off little, and we got good feedback from the neighborhood kids. And we’re always like, ‘What can we do better or what can we do more of?’ And it has just grown over the years to what we have now.”\n\n,\n\nThe display has grown so much she had to buy a second shed just to store it.\n\n, \n\n## [10 must-see Halloween houses in Richmond](https://richmond.com/life-entertainment/local/article_d2527709-fe7b-4d55-a846-db440bc7f8eb.html)\n\nIf you think Richmond is creative the rest of the year, just wait until Halloween. From giant skeletons and fog-filled graveyards to entire streets transformed overnight, neighborhoods across the city go all out to get spooky.\n\n,\n\n“I even have a casket that’s an actual Hollywood prop. Just the casket, no dead bodies,” she joked.\n\n,",
      "content": ", [![](https://bloximages.newyork1.vip.townnews.com/richmond.com/content/tncms/assets/v3/editorial/a/f2/af22ec18-2ba4-4fb2-b6da-3375e85df917/68f8edb2b810b.image.jpg?resize=100%2C67)](https://richmond.com/image_af22ec18-2ba4-4fb2-b6da-3375e85df917.html)\n\n## [10xx25-rtd-met-halloween](https://richmond.com/image_af22ec18-2ba4-4fb2-b6da-3375e85df917.html)\n\n“We like putting a smile on the kids’ faces,” Julie Watson said. “When schools let out, there’s a line of cars just rolling slowly, looking at our display.”\n\n,\n,\n\n“For myself, it was the pumpkin scarecrow. I sat in front of the casket, slumped over in a chair, and then I would tap on the casket, and I’d say, ‘Boo.’ They thought I was a prop,” she said. “We started off little, and we got good feedback from the neighborhood kids. And we’re always like, ‘What can we do better or what can we do more of?’ And it has just grown over the years to what we have now.”\n\n,\n\nThe display has grown so much she had to buy a second shed just to store it.\n\n, \n\n## [10 must-see Halloween houses in Richmond](https://richmond.com/life-entertainment/local/article_d2527709-fe7b-4d55-a846-db440bc7f8eb.html)\n\nIf you think Richmond is creative the rest of the year, just wait until Halloween. From giant skeletons and fog-filled graveyards to entire streets transformed overnight, neighborhoods across the city go all out to get spooky.\n\n,\n\n“I even have a casket that’s an actual Hollywood prop. Just the casket, no dead bodies,” she joked.\n\n,"
    },
    {
      "include": true,
      "schema_version": "2.0",
      "chunk_metadata": {
        "id": "00324fabf598c68fe0e88707b3929d212d22a65a526b923496b49a2e71a46fdd-0",
        "idx": 0,
        "hash": "48d9e93454883c3a939c2b0aa723859f613bbb55dbde84d7ec50efd0c45a80d0"
      },
      "content_original": "[\n\nRichmond’s neighborhoods come alive each October with the Halloween spirit, ranging from downright frightening to kid-friendly whimsy.\n\n,\n\nThere are animatronics, zombie takeovers, parades and plenty of 12-foot skeletons standing guard.\n\n,\n\nHalloween is near, so let the boos begin.\n\n, [![](https://bloximages.newyork1.vip.townnews.com/richmond.com/content/tncms/assets/v3/editorial/4/f1/4f120014-1aa5-4d34-b830-4b3a29662960/68f8ed92b4bf9.image.jpg?resize=100%2C67)](https://richmond.com/image_4f120014-1aa5-4d34-b830-4b3a29662960.html)\n\n## [10xx25-rtd-met-halloween](https://richmond.com/image_4f120014-1aa5-4d34-b830-4b3a29662960.html)\n\nJulie Watson and Bill McNeill have turned their home at 10533 Ashburn Road in North Chesterfield into a spooky Halloween spectacle.\n\n,",
      "content": "[\n\nRichmond’s neighborhoods come alive each October with the Halloween spirit, ranging from downright frightening to kid-friendly whimsy.\n\n,\n\nThere are animatronics, zombie takeovers, parades and plenty of 12-foot skeletons standing guard.\n\n,\n\nHalloween is near, so let the boos begin.\n\n, [![](https://bloximages.newyork1.vip.townnews.com/richmond.com/content/tncms/assets/v3/editorial/4/f1/4f120014-1aa5-4d34-b830-4b3a29662960/68f8ed92b4bf9.image.jpg?resize=100%2C67)](https://richmond.com/image_4f120014-1aa5-4d34-b830-4b3a29662960.html)\n\n## [10xx25-rtd-met-halloween](https://richmond.com/image_4f120014-1aa5-4d34-b830-4b3a29662960.html)\n\nJulie Watson and Bill McNeill have turned their home at 10533 Ashburn Road in North Chesterfield into a spooky Halloween spectacle.\n\n,"
    },
    {
      "include": true,
      "schema_version": "2.0",
      "chunk_metadata": {
        "id": "00324fabf598c68fe0e88707b3929d212d22a65a526b923496b49a2e71a46fdd-8",
        "idx": 8,
        "hash": "58c067845e164c728a201be6226226d9bbd94400501e9ddb0095b4b509c99eb7"
      },
      "content_original": ",\n\nAnd of course, **Hanover Avenue, the Bellevue Neighborhood,** and **Church Hill** are always hot spots for trick-or-treating.\n\n, [![](https://bloximages.newyork1.vip.townnews.com/richmond.com/content/tncms/assets/v3/editorial/e/71/e717f310-97e2-11ef-a20c-9f3f0e00a188/672418738c7be.preview.jpg?resize=100%2C67)](https://richmond.com/life-entertainment/local/collection_e717f310-97e2-11ef-a20c-9f3f0e00a188.html)\n\n## [Trick-or-treating in Richmond on Halloween 2024](https://richmond.com/life-entertainment/local/collection_e717f310-97e2-11ef-a20c-9f3f0e00a188.html)\n\n]",
      "content": ",\n\nAnd of course, **Hanover Avenue, the Bellevue Neighborhood,** and **Church Hill** are always hot spots for trick-or-treating.\n\n, [![](https://bloximages.newyork1.vip.townnews.com/richmond.com/content/tncms/assets/v3/editorial/e/71/e717f310-97e2-11ef-a20c-9f3f0e00a188/672418738c7be.preview.jpg?resize=100%2C67)](https://richmond.com/life-entertainment/local/collection_e717f310-97e2-11ef-a20c-9f3f0e00a188.html)\n\n## [Trick-or-treating in Richmond on Halloween 2024](https://richmond.com/life-entertainment/local/collection_e717f310-97e2-11ef-a20c-9f3f0e00a188.html)\n\n]"
    }
  ],
  "ingest_metadata": [
    {
      "_id": "67d52def-90ff-4691-bc5f-c730c03a33ca",
      "timestamp": "2025-10-23T21:32:52.295000",
      "success": true,
      "failure_reason": null,
      "publisher_id": "242e6934-d98d-4b91-a9a9-f6a425f85938",
      "version": "2.3",
      "date": "2025-10-23",
      "chunking": {
        "chunks_count": 9
      },
      "context_generating": {
        "strategy": "none"
      },
      "embedding": {
        "provider": "voyage",
        "model": "voyage-3-large",
        "dimension": 2048,
        "data_type": "binary"
      },
      "indexing": {
        "chunks_success_count": 9,
        "chunks_failed_count": 0,
        "index_names": [
          "lee_enterprises_index_v2"
        ]
      },
      "document_id": "00324fabf598c68fe0e88707b3929d212d22a65a526b923496b49a2e71a46fdd"
    }
  ],
  "raw_content": "{\n  \"uuid\" : \"8b8c8cff-5777-4e29-93ea-184e6cba8673\",\n  \"title\" : \"Where to find the best Halloween decorations around Richmond\",\n  \"type\" : \"article\",\n  \"presentation\" : \"personality\",\n  \"url\" : \"https://richmond.com/life-entertainment/local/article_8b8c8cff-5777-4e29-93ea-184e6cba8673.html\",\n  \"lastupdated\" : {\n    \"utc\" : null,\n    \"iso8601\" : null,\n    \"rfc2822\" : null\n  },\n  \"starttime\" : {\n    \"utc\" : \"1761215400000\",\n    \"iso8601\" : \"2025-10-23T06:30:00-04:00\",\n    \"rfc2822\" : \"Thu, 23 Oct 2025 06:30:00 -0400\"\n  },\n  \"archivetime\" : {\n    \"utc\" : null,\n    \"iso8601\" : null,\n    \"rfc2822\" : null\n  },\n  \"keywords\" : [ \"halloween\", \"#newsvudone\", \"evergreen\" ],\n  \"sections\" : [ \"life-entertainment/local\" ],\n  \"flags\" : [ \"alert\", \"top_story\" ],\n  \"thumbnail\" : {\n    \"mode\" : \"via .view\",\n    \"uuid\" : \"8b8c8cff-5777-4e29-93ea-184e6cba8673\",\n    \"aspect_ratio\" : \"100:67\",\n    \"aspect_ratio_x\" : 100,\n    \"aspect_ratio_y\" : 67,\n    \"file_size\" : 623357,\n    \"height\" : 67,\n    \"mime_type\" : \"image/jpeg\",\n    \"url\" : \"https://bloximages.newyork1.vip.townnews.com/richmond.com/content/tncms/assets/v3/editorial/8/b8/8b8c8cff-5777-4e29-93ea-184e6cba8673/68f8f2417e7c9.preview.jpg?resize=100%2C67\",\n    \"resource_url\" : \"https://bloximages.newyork1.vip.townnews.com/richmond.com/content/tncms/assets/v3/editorial/8/b8/8b8c8cff-5777-4e29-93ea-184e6cba8673/68f8f2417e7c9.preview.jpg?resize=100%2C67\",\n    \"width\" : 100\n  },\n  \"preview\" : {\n    \"mode\" : \"via .view\",\n    \"uuid\" : \"8b8c8cff-5777-4e29-93ea-184e6cba8673\",\n    \"aspect_ratio\" : \"640:427\",\n    \"aspect_ratio_x\" : 640,\n    \"aspect_ratio_y\" : 427,\n    \"file_size\" : 623357,\n    \"height\" : 427,\n    \"mime_type\" : \"image/jpeg\",\n    \"url\" : \"https://bloximages.newyork1.vip.townnews.com/richmond.com/content/tncms/assets/v3/editorial/8/b8/8b8c8cff-5777-4e29-93ea-184e6cba8673/68f8f2417e7c9.preview.jpg?resize=640%2C427\",\n    \"resource_url\" : \"https://bloximages.newyork1.vip.townnews.com/richmond.com/content/tncms/assets/v3/editorial/8/b8/8b8c8cff-5777-4e29-93ea-184e6cba8673/68f8f2417e7c9.preview.jpg?resize=640%2C427\",\n    \"width\" : 640\n  },\n  \"section_label\" : \"Local\",\n  \"authors\" : [ {\n    \"uuid\" : \"c440f4e6-0967-11ee-89ff-17678951e325\",\n    \"first_name\" : \"Chelsea \",\n    \"last_name\" : \"Jackson\",\n    \"full_name\" : \"Chelsea  Jackson\",\n    \"screen_name\" : \"Chelsea Jackson\",\n    \"byline\" : \"CHELSEA JACKSON\\nRichmond Times-Dispatch \",\n    \"avatar\" : \"https://bloximages.newyork1.vip.townnews.com/richmond.com/content/tncms/avatars/c/44/0f4/c440f4e6-0967-11ee-89ff-17678951e325.49af20eda84f69c3309b5a87998db507.png?_dc=1707243209\",\n    \"title\" : \"Features Reporter\",\n    \"profile\" : \"richmond.com/users/profile/Chelsea Jackson\"\n  } ],\n  \"prologue\" : \"<p>Check out these spook-tacular decorations from The Fan to the suburbs. </p>\",\n  \"subheadline\" : \"\",\n  \"tagline\" : \"<p><strong>Chelsea Jackson</strong><!--p:BC TAG Body Copy Tagline--> <!--p:BC TAG Body Copy Tagline--></p><p>(804) 649-6965 <!--p:BC TAG Body Copy Tagline--></p><p>cjackson@timesdispatch.com<!--p:BC TAG Body Copy Tagline--></p>\",\n  \"byline\" : \"CHELSEA JACKSON\\nRichmond Times-Dispatch\",\n  \"hammer\" : \"\",\n  \"kicker\" : \"\",\n  \"content\" : [ \"<p>Richmond’s neighborhoods come alive each October with the Halloween spirit, ranging from downright frightening to kid-friendly whimsy.</p>\", \"<p>There are animatronics, zombie takeovers, parades and plenty of 12-foot skeletons standing guard.</p>\", \"<p>Halloween is near, so let the boos begin.</p>\", \"<figure class=\\\"inline-asset inline-editorial-image\\\" data-tncms-app=\\\"editorial\\\" data-tncms-uuid=\\\"4f120014-1aa5-4d34-b830-4b3a29662960\\\"><a href=\\\"https://richmond.com/image_4f120014-1aa5-4d34-b830-4b3a29662960.html\\\"><img src=\\\"https://bloximages.newyork1.vip.townnews.com/richmond.com/content/tncms/assets/v3/editorial/4/f1/4f120014-1aa5-4d34-b830-4b3a29662960/68f8ed92b4bf9.image.jpg?resize=100%2C67\\\"></a><figcaption><h2><a href=\\\"https://richmond.com/image_4f120014-1aa5-4d34-b830-4b3a29662960.html\\\"><i class=\\\"far tnt-image\\\" aria-hidden=\\\"true\\\"></i> 10xx25-rtd-met-halloween</a></h2><p>Julie Watson and Bill McNeill have turned their home at 10533 Ashburn Road in North Chesterfield into a spooky Halloween spectacle. </p></figcaption></figure>\", \"<p>In North Chesterfield at <strong>10533 Ashburn Road,</strong> Julie Watson and Bill McNeill, both 58, are ready to collect some screams. Every inch of the yard is part of the performance. There’s fog, homemade tombstones, Annabelle hanging in the trees, and scare actors hiding in plain sight. What started as small yard decorations has turned into a full-scale production.</p>\", \"<p>Watson says Halloween has always been a favorite holiday. “It comes from a very young age. I love dressing up,” she said. “You get dressed up and you get candy. What kid does not want to do that?”</p>\", \"<p>That love of Halloween rolled over into making costumes for her children, doing hands-on DIY projects, and entering contests.</p>\", \"<p>Her top costumes include a Rubik’s cube and a Chinese food to-go box for her son. One year, he won three costume contests helping Julie secure $3,000 off of his braces.</p>\", \"<figure class=\\\"inline-asset inline-editorial-image\\\" data-tncms-app=\\\"editorial\\\" data-tncms-uuid=\\\"af22ec18-2ba4-4fb2-b6da-3375e85df917\\\"><a href=\\\"https://richmond.com/image_af22ec18-2ba4-4fb2-b6da-3375e85df917.html\\\"><img src=\\\"https://bloximages.newyork1.vip.townnews.com/richmond.com/content/tncms/assets/v3/editorial/a/f2/af22ec18-2ba4-4fb2-b6da-3375e85df917/68f8edb2b810b.image.jpg?resize=100%2C67\\\"></a><figcaption><h2><a href=\\\"https://richmond.com/image_af22ec18-2ba4-4fb2-b6da-3375e85df917.html\\\"><i class=\\\"far tnt-image\\\" aria-hidden=\\\"true\\\"></i> 10xx25-rtd-met-halloween</a></h2><p>“We like putting a smile on the kids’ faces,” Julie Watson said. “When schools let out, there’s a line of cars just rolling slowly, looking at our display.” </p></figcaption></figure>\", \"<p>“For myself, it was the pumpkin scarecrow. I sat in front of the casket, slumped over in a chair, and then I would tap on the casket, and I’d say, ‘Boo.’ They thought I was a prop,” she said. “We started off little, and we got good feedback from the neighborhood kids. And we’re always like, ‘What can we do better or what can we do more of?’ And it has just grown over the years to what we have now.”</p>\", \"<p>The display has grown so much she had to buy a second shed just to store it.</p>\", \"<figure class=\\\"inline-asset inline-editorial-article\\\" data-tncms-app=\\\"editorial\\\" data-tncms-uuid=\\\"d2527709-fe7b-4d55-a846-db440bc7f8eb\\\"><figcaption><h2><a href=\\\"https://richmond.com/life-entertainment/local/article_d2527709-fe7b-4d55-a846-db440bc7f8eb.html\\\"><i class=\\\"fas tnt-file-alt\\\" aria-hidden=\\\"true\\\"></i> 10 must-see Halloween houses in Richmond</a></h2><p>If you think Richmond is creative the rest of the year, just wait until Halloween. From giant skeletons and fog-filled graveyards to entire streets transformed overnight, neighborhoods across the city go all out to get spooky. </p></figcaption></figure>\", \"<p>“I even have a casket that’s an actual Hollywood prop. Just the casket, no dead bodies,” she joked.</p>\", \"<p>“We like putting a smile on the kids’ faces,” she added. “Our house is off Huguenot Road between St. Edward’s Church and Huguenot Church, so we get a lot of traffic. When schools let out, there’s a line of cars just rolling slowly, looking at our display.”</p>\", \"<figure class=\\\"inline-asset inline-editorial-image\\\" data-tncms-app=\\\"editorial\\\" data-tncms-uuid=\\\"ee9f5caa-989a-476e-b125-d0750cf9bfff\\\"><a href=\\\"https://richmond.com/image_ee9f5caa-989a-476e-b125-d0750cf9bfff.html\\\"><img src=\\\"https://bloximages.newyork1.vip.townnews.com/richmond.com/content/tncms/assets/v3/editorial/e/e9/ee9f5caa-989a-476e-b125-d0750cf9bfff/68f8ed7e638c4.image.jpg?resize=100%2C67\\\"></a><figcaption><h2><a href=\\\"https://richmond.com/image_ee9f5caa-989a-476e-b125-d0750cf9bfff.html\\\"><i class=\\\"far tnt-image\\\" aria-hidden=\\\"true\\\"></i> 10xx25-rtd-met-halloween</a></h2><p>A giant animatronic werewolf is part of the halloween decorations at 10533 Ashburn Road in North Chesterfield. </p></figcaption></figure>\", \"<p>This year, they’re extending their display to include a Halloween tunnel in the driveway and another in the backyard.</p>\", \"<p>“That one’s going to be a little bit scarier,” she said. “We’re going to hire some actors, volunteer actors, to do some little jump scares. We have all these ambitious ideas, and trying to make them come to real life is a challenge but we enjoy it, myself and my husband. As long as we’ve got good knees and a good back.”</p>\", \"<p>The couple starts prepping early.</p>\", \"<p>“We start staging in the backyard in June to make sure they’re working, if they need any touch-ups or repairs,” she said. “We had one of the 12-foot skeletons fall over last year, so his ribs were broken. So right now, we’re doing some plastic surgery on him.”</p>\", \"<p>Her two youngest children still help out, offering ideas and dressing up every year. “Because you live in my house, you got to dress up,” she said.</p>\", \"<figure class=\\\"inline-asset inline-editorial-image\\\" data-tncms-app=\\\"editorial\\\" data-tncms-uuid=\\\"130bc762-ea2c-4d10-82dd-f4f3d9f0f935\\\"><a href=\\\"https://richmond.com/image_130bc762-ea2c-4d10-82dd-f4f3d9f0f935.html\\\"><img src=\\\"https://bloximages.newyork1.vip.townnews.com/richmond.com/content/tncms/assets/v3/editorial/1/30/130bc762-ea2c-4d10-82dd-f4f3d9f0f935/68f7036113997.image.jpg?resize=100%2C75\\\"></a><figcaption><h2><a href=\\\"https://richmond.com/image_130bc762-ea2c-4d10-82dd-f4f3d9f0f935.html\\\"><i class=\\\"far tnt-image\\\" aria-hidden=\\\"true\\\"></i> Harry Potter house on Floyd Ave.</a></h2><p>Every year, the Harry Potter house at 3433 Floyd Ave. gets decorated to the theme of a different Harry Potter book. </p></figcaption></figure>\", \"<p><strong>More must-see Halloween houses around Richmond</strong>The app Fright maps has an up-to-date list of decorated Halloween houses in the area like the haunted house at <strong>4913 Sadler Glen Place in Glen Allen</strong> with plenty of pumpkins, tombstones and even Jack Skellington.</p>\", \"<p>Head to <strong>2105 Maplewood Road</strong> for the Dark Woods of Lakeside or 9420 Gayton Road for skeletons, lights, witches, cauldrons and giant spiders.</p>\", \"<p>If you’re looking for something more fanciful, head to <strong>3433 Floyd Ave.</strong> in the Museum District for the Harry Potter House where Kyle and Sarah Rasmussen have turned their house into a page from a book.</p>\", \"<p>“Halloween has always been a big thing in my family. My parents both enjoyed Halloween and decorated a lot when I was a kid,” Kyle said. “I’ve done Harry Potter the last six years that we’ve lived in Richmond. Each year, we do the next book.”</p>\", \"<p>This year is “Harry Potter and the Half-Blood Prince.”</p>\", \"<p>“Every year there’s some old favorites, like the werewolves and the spiders and the dragon on top of the carport,” she said. “But the whole front of the house is completely different.”</p>\", \"<p>The house has become a local favorite and a social media hit.</p>\", \"<p>“We usually have a lot of people stopping by,” he said. “Towards Halloween, we’ll probably get like 50 to 100 people during the day that will walk by it.”</p>\", \"<p>At night, Kyle says it’s too many to count.</p>\", \"<p>Preparation starts early. “I used to wait till the first week of October, but since we have two small kids now, I start the second week of September just because it takes a little bit longer. And that time only gives me so much time to put stuff up.”</p>\", \"<p>In Henrico, <strong><a href=\\\"https://www.facebook.com/profile.php?id=61558301124456\\\" target=\\\"_blank\\\">The Haunt in Chamberlayne Farms</a></strong> is back with a haunted walk-through experience at 5914 Chamberlayne Road. </p>\", \"<p>Oregon Hill has many Halloween decorated houses in preparation for the <strong><a href=\\\"https://www.facebook.com/allthesaintstheatercompany\\\" target=\\\"_blank\\\">All the Saints Theater Company’s 20th annual Halloween Parade</a></strong> on Oct. 31.</p>\", \"<p>And of course, <strong>Hanover Avenue, the Bellevue Neighborhood,</strong> and <strong>Church Hill</strong> are always hot spots for trick-or-treating.</p>\", \"<figure class=\\\"inline-asset inline-editorial-collection\\\" data-tncms-app=\\\"editorial\\\" data-tncms-uuid=\\\"e717f310-97e2-11ef-a20c-9f3f0e00a188\\\"><a href=\\\"https://richmond.com/life-entertainment/local/collection_e717f310-97e2-11ef-a20c-9f3f0e00a188.html\\\"><img src=\\\"https://bloximages.newyork1.vip.townnews.com/richmond.com/content/tncms/assets/v3/editorial/e/71/e717f310-97e2-11ef-a20c-9f3f0e00a188/672418738c7be.preview.jpg?resize=100%2C67\\\"></a><figcaption><h2><a href=\\\"https://richmond.com/life-entertainment/local/collection_e717f310-97e2-11ef-a20c-9f3f0e00a188.html\\\"><i class=\\\"far tnt-copy\\\" aria-hidden=\\\"true\\\"></i> Trick-or-treating in Richmond on Halloween 2024</a></h2><p></p></figcaption></figure>\" ]\n}",
  "markdown_content": "[\n\nRichmond’s neighborhoods come alive each October with the Halloween spirit, ranging from downright frightening to kid-friendly whimsy.\n\n,\n\nThere are animatronics, zombie takeovers, parades and plenty of 12-foot skeletons standing guard.\n\n,\n\nHalloween is near, so let the boos begin.\n\n, [![](https://bloximages.newyork1.vip.townnews.com/richmond.com/content/tncms/assets/v3/editorial/4/f1/4f120014-1aa5-4d34-b830-4b3a29662960/68f8ed92b4bf9.image.jpg?resize=100%2C67)](https://richmond.com/image_4f120014-1aa5-4d34-b830-4b3a29662960.html)\n\n## [10xx25-rtd-met-halloween](https://richmond.com/image_4f120014-1aa5-4d34-b830-4b3a29662960.html)\n\nJulie Watson and Bill McNeill have turned their home at 10533 Ashburn Road in North Chesterfield into a spooky Halloween spectacle.\n\n,\n\nIn North Chesterfield at **10533 Ashburn Road,** Julie Watson and Bill McNeill, both 58, are ready to collect some screams. Every inch of the yard is part of the performance. There’s fog, homemade tombstones, Annabelle hanging in the trees, and scare actors hiding in plain sight. What started as small yard decorations has turned into a full-scale production.\n\n,\n\nWatson says Halloween has always been a favorite holiday. “It comes from a very young age. I love dressing up,” she said. “You get dressed up and you get candy. What kid does not want to do that?”\n\n,\n\nThat love of Halloween rolled over into making costumes for her children, doing hands-on DIY projects, and entering contests.\n\n,\n\nHer top costumes include a Rubik’s cube and a Chinese food to-go box for her son. One year, he won three costume contests helping Julie secure $3,000 off of his braces.\n\n, [![](https://bloximages.newyork1.vip.townnews.com/richmond.com/content/tncms/assets/v3/editorial/a/f2/af22ec18-2ba4-4fb2-b6da-3375e85df917/68f8edb2b810b.image.jpg?resize=100%2C67)](https://richmond.com/image_af22ec18-2ba4-4fb2-b6da-3375e85df917.html)\n\n## [10xx25-rtd-met-halloween](https://richmond.com/image_af22ec18-2ba4-4fb2-b6da-3375e85df917.html)\n\n“We like putting a smile on the kids’ faces,” Julie Watson said. “When schools let out, there’s a line of cars just rolling slowly, looking at our display.”\n\n,\n\n“For myself, it was the pumpkin scarecrow. I sat in front of the casket, slumped over in a chair, and then I would tap on the casket, and I’d say, ‘Boo.’ They thought I was a prop,” she said. “We started off little, and we got good feedback from the neighborhood kids. And we’re always like, ‘What can we do better or what can we do more of?’ And it has just grown over the years to what we have now.”\n\n,\n\nThe display has grown so much she had to buy a second shed just to store it.\n\n, \n\n## [10 must-see Halloween houses in Richmond](https://richmond.com/life-entertainment/local/article_d2527709-fe7b-4d55-a846-db440bc7f8eb.html)\n\nIf you think Richmond is creative the rest of the year, just wait until Halloween. From giant skeletons and fog-filled graveyards to entire streets transformed overnight, neighborhoods across the city go all out to get spooky.\n\n,\n\n“I even have a casket that’s an actual Hollywood prop. Just the casket, no dead bodies,” she joked.\n\n,\n\n“We like putting a smile on the kids’ faces,” she added. “Our house is off Huguenot Road between St. Edward’s Church and Huguenot Church, so we get a lot of traffic. When schools let out, there’s a line of cars just rolling slowly, looking at our display.”\n\n, [![](https://bloximages.newyork1.vip.townnews.com/richmond.com/content/tncms/assets/v3/editorial/e/e9/ee9f5caa-989a-476e-b125-d0750cf9bfff/68f8ed7e638c4.image.jpg?resize=100%2C67)](https://richmond.com/image_ee9f5caa-989a-476e-b125-d0750cf9bfff.html)\n\n## [10xx25-rtd-met-halloween](https://richmond.com/image_ee9f5caa-989a-476e-b125-d0750cf9bfff.html)\n\nA giant animatronic werewolf is part of the halloween decorations at 10533 Ashburn Road in North Chesterfield.\n\n,\n\nThis year, they’re extending their display to include a Halloween tunnel in the driveway and another in the backyard.\n\n,\n\n“That one’s going to be a little bit scarier,” she said. “We’re going to hire some actors, volunteer actors, to do some little jump scares. We have all these ambitious ideas, and trying to make them come to real life is a challenge but we enjoy it, myself and my husband. As long as we’ve got good knees and a good back.”\n\n,\n\nThe couple starts prepping early.\n\n,\n\n“We start staging in the backyard in June to make sure they’re working, if they need any touch-ups or repairs,” she said. “We had one of the 12-foot skeletons fall over last year, so his ribs were broken. So right now, we’re doing some plastic surgery on him.”\n\n,\n\nHer two youngest children still help out, offering ideas and dressing up every year. “Because you live in my house, you got to dress up,” she said.\n\n, [![](https://bloximages.newyork1.vip.townnews.com/richmond.com/content/tncms/assets/v3/editorial/1/30/130bc762-ea2c-4d10-82dd-f4f3d9f0f935/68f7036113997.image.jpg?resize=100%2C75)](https://richmond.com/image_130bc762-ea2c-4d10-82dd-f4f3d9f0f935.html)\n\n## [Harry Potter house on Floyd Ave.](https://richmond.com/image_130bc762-ea2c-4d10-82dd-f4f3d9f0f935.html)\n\nEvery year, the Harry Potter house at 3433 Floyd Ave. gets decorated to the theme of a different Harry Potter book.\n\n,\n\n**More must-see Halloween houses around Richmond**The app Fright maps has an up-to-date list of decorated Halloween houses in the area like the haunted house at **4913 Sadler Glen Place in Glen Allen** with plenty of pumpkins, tombstones and even Jack Skellington.\n\n,\n\nHead to **2105 Maplewood Road** for the Dark Woods of Lakeside or 9420 Gayton Road for skeletons, lights, witches, cauldrons and giant spiders.\n\n,\n\nIf you’re looking for something more fanciful, head to **3433 Floyd Ave.** in the Museum District for the Harry Potter House where Kyle and Sarah Rasmussen have turned their house into a page from a book.\n\n,\n\n“Halloween has always been a big thing in my family. My parents both enjoyed Halloween and decorated a lot when I was a kid,” Kyle said. “I’ve done Harry Potter the last six years that we’ve lived in Richmond. Each year, we do the next book.”\n\n,\n\nThis year is “Harry Potter and the Half-Blood Prince.”\n\n,\n\n“Every year there’s some old favorites, like the werewolves and the spiders and the dragon on top of the carport,” she said. “But the whole front of the house is completely different.”\n\n,\n\nThe house has become a local favorite and a social media hit.\n\n,\n\n“We usually have a lot of people stopping by,” he said. “Towards Halloween, we’ll probably get like 50 to 100 people during the day that will walk by it.”\n\n,\n\nAt night, Kyle says it’s too many to count.\n\n,\n\nPreparation starts early. “I used to wait till the first week of October, but since we have two small kids now, I start the second week of September just because it takes a little bit longer. And that time only gives me so much time to put stuff up.”\n\n,\n\nIn Henrico, **[The Haunt in Chamberlayne Farms](https://www.facebook.com/profile.php?id=61558301124456)** is back with a haunted walk-through experience at 5914 Chamberlayne Road.\n\n,\n\nOregon Hill has many Halloween decorated houses in preparation for the **[All the Saints Theater Company’s 20th annual Halloween Parade](https://www.facebook.com/allthesaintstheatercompany)** on Oct. 31.\n\n,\n\nAnd of course, **Hanover Avenue, the Bellevue Neighborhood,** and **Church Hill** are always hot spots for trick-or-treating.\n\n, [![](https://bloximages.newyork1.vip.townnews.com/richmond.com/content/tncms/assets/v3/editorial/e/71/e717f310-97e2-11ef-a20c-9f3f0e00a188/672418738c7be.preview.jpg?resize=100%2C67)](https://richmond.com/life-entertainment/local/collection_e717f310-97e2-11ef-a20c-9f3f0e00a188.html)\n\n## [Trick-or-treating in Richmond on Halloween 2024](https://richmond.com/life-entertainment/local/collection_e717f310-97e2-11ef-a20c-9f3f0e00a188.html)\n\n]",
  "removed_blocks": [],
  "edited_blocks": [],
  "block_comments": [],
  "label_status": "not_started",
  "doc_comment": "",
  "labeler": "chunshui@prorata.ai",
  "cleaned_content": "[\n\nRichmond’s neighborhoods come alive each October with the Halloween spirit, ranging from downright frightening to kid-friendly whimsy.\n\n,\n\nThere are animatronics, zombie takeovers, parades and plenty of 12-foot skeletons standing guard.\n\n,\n\nHalloween is near, so let the boos begin.\n\n, [![](https://bloximages.newyork1.vip.townnews.com/richmond.com/content/tncms/assets/v3/editorial/4/f1/4f120014-1aa5-4d34-b830-4b3a29662960/68f8ed92b4bf9.image.jpg?resize=100%2C67)](https://richmond.com/image_4f120014-1aa5-4d34-b830-4b3a29662960.html)\n\n## [10xx25-rtd-met-halloween](https://richmond.com/image_4f120014-1aa5-4d34-b830-4b3a29662960.html)\n\nJulie Watson and Bill McNeill have turned their home at 10533 Ashburn Road in North Chesterfield into a spooky Halloween spectacle.\n\n,\n\nIn North Chesterfield at **10533 Ashburn Road,** Julie Watson and Bill McNeill, both 58, are ready to collect some screams. Every inch of the yard is part of the performance. There’s fog, homemade tombstones, Annabelle hanging in the trees, and scare actors hiding in plain sight. What started as small yard decorations has turned into a full-scale production.\n\n,\n\nWatson says Halloween has always been a favorite holiday. “It comes from a very young age. I love dressing up,” she said. “You get dressed up and you get candy. What kid does not want to do that?”\n\n,\n\nThat love of Halloween rolled over into making costumes for her children, doing hands-on DIY projects, and entering contests.\n\n,\n\nHer top costumes include a Rubik’s cube and a Chinese food to-go box for her son. One year, he won three costume contests helping Julie secure $3,000 off of his braces.\n\n, [![](https://bloximages.newyork1.vip.townnews.com/richmond.com/content/tncms/assets/v3/editorial/a/f2/af22ec18-2ba4-4fb2-b6da-3375e85df917/68f8edb2b810b.image.jpg?resize=100%2C67)](https://richmond.com/image_af22ec18-2ba4-4fb2-b6da-3375e85df917.html)\n\n## [10xx25-rtd-met-halloween](https://richmond.com/image_af22ec18-2ba4-4fb2-b6da-3375e85df917.html)\n\n“We like putting a smile on the kids’ faces,” Julie Watson said. “When schools let out, there’s a line of cars just rolling slowly, looking at our display.”\n\n,\n\n“For myself, it was the pumpkin scarecrow. I sat in front of the casket, slumped over in a chair, and then I would tap on the casket, and I’d say, ‘Boo.’ They thought I was a prop,” she said. “We started off little, and we got good feedback from the neighborhood kids. And we’re always like, ‘What can we do better or what can we do more of?’ And it has just grown over the years to what we have now.”\n\n,\n\nThe display has grown so much she had to buy a second shed just to store it.\n\n, \n\n## [10 must-see Halloween houses in Richmond](https://richmond.com/life-entertainment/local/article_d2527709-fe7b-4d55-a846-db440bc7f8eb.html)\n\nIf you think Richmond is creative the rest of the year, just wait until Halloween. From giant skeletons and fog-filled graveyards to entire streets transformed overnight, neighborhoods across the city go all out to get spooky.\n\n,\n\n“I even have a casket that’s an actual Hollywood prop. Just the casket, no dead bodies,” she joked.\n\n,\n\n“We like putting a smile on the kids’ faces,” she added. “Our house is off Huguenot Road between St. Edward’s Church and Huguenot Church, so we get a lot of traffic. When schools let out, there’s a line of cars just rolling slowly, looking at our display.”\n\n, [![](https://bloximages.newyork1.vip.townnews.com/richmond.com/content/tncms/assets/v3/editorial/e/e9/ee9f5caa-989a-476e-b125-d0750cf9bfff/68f8ed7e638c4.image.jpg?resize=100%2C67)](https://richmond.com/image_ee9f5caa-989a-476e-b125-d0750cf9bfff.html)\n\n## [10xx25-rtd-met-halloween](https://richmond.com/image_ee9f5caa-989a-476e-b125-d0750cf9bfff.html)\n\nA giant animatronic werewolf is part of the halloween decorations at 10533 Ashburn Road in North Chesterfield.\n\n,\n\nThis year, they’re extending their display to include a Halloween tunnel in the driveway and another in the backyard.\n\n,\n\n“That one’s going to be a little bit scarier,” she said. “We’re going to hire some actors, volunteer actors, to do some little jump scares. We have all these ambitious ideas, and trying to make them come to real life is a challenge but we enjoy it, myself and my husband. As long as we’ve got good knees and a good back.”\n\n,\n\nThe couple starts prepping early.\n\n,\n\n“We start staging in the backyard in June to make sure they’re working, if they need any touch-ups or repairs,” she said. “We had one of the 12-foot skeletons fall over last year, so his ribs were broken. So right now, we’re doing some plastic surgery on him.”\n\n,\n\nHer two youngest children still help out, offering ideas and dressing up every year. “Because you live in my house, you got to dress up,” she said.\n\n, [![](https://bloximages.newyork1.vip.townnews.com/richmond.com/content/tncms/assets/v3/editorial/1/30/130bc762-ea2c-4d10-82dd-f4f3d9f0f935/68f7036113997.image.jpg?resize=100%2C75)](https://richmond.com/image_130bc762-ea2c-4d10-82dd-f4f3d9f0f935.html)\n\n## [Harry Potter house on Floyd Ave.](https://richmond.com/image_130bc762-ea2c-4d10-82dd-f4f3d9f0f935.html)\n\nEvery year, the Harry Potter house at 3433 Floyd Ave. gets decorated to the theme of a different Harry Potter book.\n\n,\n\n**More must-see Halloween houses around Richmond**The app Fright maps has an up-to-date list of decorated Halloween houses in the area like the haunted house at **4913 Sadler Glen Place in Glen Allen** with plenty of pumpkins, tombstones and even Jack Skellington.\n\n,\n\nHead to **2105 Maplewood Road** for the Dark Woods of Lakeside or 9420 Gayton Road for skeletons, lights, witches, cauldrons and giant spiders.\n\n,\n\nIf you’re looking for something more fanciful, head to **3433 Floyd Ave.** in the Museum District for the Harry Potter House where Kyle and Sarah Rasmussen have turned their house into a page from a book.\n\n,\n\n“Halloween has always been a big thing in my family. My parents both enjoyed Halloween and decorated a lot when I was a kid,” Kyle said. “I’ve done Harry Potter the last six years that we’ve lived in Richmond. Each year, we do the next book.”\n\n,\n\nThis year is “Harry Potter and the Half-Blood Prince.”\n\n,\n\n“Every year there’s some old favorites, like the werewolves and the spiders and the dragon on top of the carport,” she said. “But the whole front of the house is completely different.”\n\n,\n\nThe house has become a local favorite and a social media hit.\n\n,\n\n“We usually have a lot of people stopping by,” he said. “Towards Halloween, we’ll probably get like 50 to 100 people during the day that will walk by it.”\n\n,\n\nAt night, Kyle says it’s too many to count.\n\n,\n\nPreparation starts early. “I used to wait till the first week of October, but since we have two small kids now, I start the second week of September just because it takes a little bit longer. And that time only gives me so much time to put stuff up.”\n\n,\n\nIn Henrico, **[The Haunt in Chamberlayne Farms](https://www.facebook.com/profile.php?id=61558301124456)** is back with a haunted walk-through experience at 5914 Chamberlayne Road.\n\n,\n\nOregon Hill has many Halloween decorated houses in preparation for the **[All the Saints Theater Company’s 20th annual Halloween Parade](https://www.facebook.com/allthesaintstheatercompany)** on Oct. 31.\n\n,\n\nAnd of course, **Hanover Avenue, the Bellevue Neighborhood,** and **Church Hill** are always hot spots for trick-or-treating.\n\n, [![](https://bloximages.newyork1.vip.townnews.com/richmond.com/content/tncms/assets/v3/editorial/e/71/e717f310-97e2-11ef-a20c-9f3f0e00a188/672418738c7be.preview.jpg?resize=100%2C67)](https://richmond.com/life-entertainment/local/collection_e717f310-97e2-11ef-a20c-9f3f0e00a188.html)\n\n## [Trick-or-treating in Richmond on Halloween 2024](https://richmond.com/life-entertainment/local/collection_e717f310-97e2-11ef-a20c-9f3f0e00a188.html)\n\n]",
  "total_blocks": 76,
  "kept_blocks": 76,
  "removed_blocks_count": 0,
  "edited_blocks_count": 0,
  "block_comments_count": 0
}